<?xml version="1.0" encoding="UTF-8"?>
<objects serializationModel="Studio.02.02.00">
	<object class="AudioFile" id="{33c4e0fa-7b4d-4d07-a814-cf26689acc8b}">
		<property name="assetPath">
			<value>asteroids/avoiding small asteroids .wav</value>
		</property>
		<property name="frequencyInKHz">
			<value>44.0999985</value>
		</property>
		<property name="channelCount">
			<value>2</value>
		</property>
		<property name="length">
			<value>5.2426757369614512</value>
		</property>
		<relationship name="masterAssetFolder">
			<destination>{baefa090-d0f8-4000-996e-91224c5ca83b}</destination>
		</relationship>
	</object>
</objects>
